LICENSE
MANIFEST.in
README.rst
django-phone-login-master.zip
requirements.txt
setup.py
authwrapper/__init__.py
authwrapper/admin.py
authwrapper/apps.py
authwrapper/fields.py
authwrapper/forms.py
authwrapper/middleware.py
authwrapper/models.py
authwrapper/tests.py
authwrapper/urls.py
authwrapper/users.py
authwrapper/validators.py
authwrapper/views.py
authwrapper/backends/__init__.py
authwrapper/backends/auth.py
authwrapper/management/__init__.py
authwrapper/management/commands/__init__.py
authwrapper/management/commands/createsuperuser2.py
authwrapper/migrations/0001_initial.py
authwrapper/migrations/0002_wechatuserprofile.py
authwrapper/migrations/0003_auto_20170710_0758.py
authwrapper/migrations/0004_auto_20171202_0837.py
authwrapper/migrations/0005_auto_20171216_1326.py
authwrapper/migrations/0006_myuser_user_role.py
authwrapper/migrations/0007_auto_20180117_2157.py
authwrapper/migrations/0008_auto_20180624_1408.py
authwrapper/migrations/__init__.py
authwrapper/static/adminlte/css/AdminLTE.min.css
authwrapper/static/adminlte/css/font-awesome.min.css
authwrapper/static/adminlte/js/adminlte.min.js
authwrapper/templates/auth/otp_sms.txt
authwrapper/templates/auth/registration_form.html
authwrapper/templates/auth/registration_form_forget.html
authwrapper/templates/auth/registration_verify_form.html
authwrapper/templates/auth/userprofile_detail.html
authwrapper/templates/auth/userprofile_list.html
authwrapper/templates/auth/userprofile_update_form.html
authwrapper/templates/registration/login.html
authwrapper/templates/rest_framework/api.html
codingsoho_auth.egg-info/PKG-INFO
codingsoho_auth.egg-info/SOURCES.txt
codingsoho_auth.egg-info/dependency_links.txt
codingsoho_auth.egg-info/requires.txt
codingsoho_auth.egg-info/top_level.txt